modgeosys/__init__.py
modgeosys/graph/__init__.py
modgeosys/graph/a_star.py
modgeosys/graph/distance.py
modgeosys/graph/edge_weight.py
modgeosys/graph/prim.py
modgeosys/graph/types.py
tests/modgeosys/graph/conftest.py
tests/modgeosys/graph/generate_a_star_test_data.py
tests/modgeosys/graph/test_a_star.py
tests/modgeosys/graph/test_distance.py
tests/modgeosys/graph/test_prim.py
tests/modgeosys/graph/test_types.py
modgeosys_graph_algorithms-0.4.3.dist-info/METADATA
modgeosys_graph_algorithms-0.4.3.dist-info/WHEEL
modgeosys_graph_algorithms-0.4.3.dist-info/RECORD
