Metadata-Version: 2.1
Name: modgeosys-graph-algorithms
Version: 0.4.3
Summary: 
Author: Kevin Weller
Author-email: klweller@icloud.com
Requires-Python: >=3.12,<4.0
Classifier: Programming Language :: Python :: 3
Classifier: Programming Language :: Python :: 3.12
Requires-Dist: heapdict (>=1.0.1,<2.0.0)
Requires-Dist: numpy (>=1.26.3,<2.0.0)
